{
    "theme": {
        "name": "Overpad",
        "parentTheme": "Darkpad",
        "iconTheme": "Dark",
        "vars": {},
        "colors": {
            "accentBg": "FFA438",
            "accentText": "FFB51E",
            "accentBright": "FFD37A",
            "background": "{{dark}}",
            "border": "{{accentBg}}",
            "buttonBg": "{{background}}",
            "buttonBgDisabled": "{{buttonBg}}",
            "buttonBgHover": "{{accentBg}}",
            "buttonBorder": "{{border}}",
            "buttonBorderDisabled": "{{buttonBorder}}",
            "buttonBorderHover": "{{buttonBorder}}",
            "buttonText": "{{textInactive}}",
            "buttonTextDisabled": "{{textDim}}",
            "buttonTextHover": "{{dark}}",
            "dark": "170F04",
            "light": "FFFFFF",
            "mainMenuBg": "{{background}}",
            "mainMenuBgDisabled": "{{background}}",
            "mainMenuBgHover": "{{background}}",
            "mainMenuBorder": "{{menuBorder}}",
            "mainMenuBorderDisabled": "{{menuBorderDisabled}}",
            "mainMenuBorderHover": "{{menuBorderHover}}",
            "mainMenuText": "{{menuText}}",
            "mainMenuTextDisabled": "{{textInactive}}",
            "mainMenuTextHover": "{{light}}",
            "manageButtonBg": "{{background}}",
            "manageButtonBgDisabled": "{{buttonBg}}",
            "manageButtonBgHover": "{{accentBg}}",
            "manageButtonBorder": "{{border}}",
            "manageButtonBorderDisabled": "{{buttonBorder}}",
            "manageButtonBorderHover": "{{buttonBorder}}",
            "manageButtonText": "{{textInactive}}",
            "manageButtonTextDisabled": "{{textDim}}",
            "manageButtonTextHover": "{{dark}}",
            "menuBg": "{{buttonBg}}",
            "menuBgDisabled": "{{buttonBgDisabled}}",
            "menuBgHover": "{{accentBg}}",
            "menuBorder": "{{buttonBorder}}",
            "menuBorderDisabled": "{{buttonBorder}}",
            "menuBorderHover": "{{buttonBorderHover}}",
            "menuText": "{{buttonText}}",
            "menuTextDisabled": "{{buttonTextDisabled}}",
            "menuTextHover": "{{dark}}",
            "primaryActionBg": "{{accentBg}}",
            "primaryActionBgDisabled": "{{buttonBgDisabled}}",
            "primaryActionBgHover": "{{accentText}}",
            "primaryActionBorder": "{{primaryActionText}}",
            "primaryActionBorderDisabled": "{{primaryActionTextDisabled}}",
            "primaryActionBorderHover": "{{primaryActionTextHover}}",
            "primaryActionText": "{{dark}}",
            "primaryActionTextDisabled": "{{dark}}",
            "primaryActionTextHover": "{{dark}}",
            "progressBarBg": "{{accentBright}}",
            "progressBarFg": "{{accentText}}",
            "statusBgActive": "{{accentBg}}",
            "statusBgActiveHover": "{{accentText}}",
            "statusBgInactive": "{{background}}",
            "statusBgInactiveHover": "{{background}}",
            "statusBorderActive": "{{light}}",
            "statusBorderActiveHover": "{{light}}",
            "statusBorderInactive": "{{light}}",
            "statusBorderInactiveHover": "{{light}}",
            "statusTextActive": "{{dark}}",
            "statusTextActiveHover": "{{dark}}",
            "statusTextInactive": "{{dark}}",
            "statusTextInactiveHover": "{{dark}}",
            "text": "{{light}}",
            "textHeading": "{{text}}",
            "textListViewHeader": "{{textHeading}}",
            "textInactive": "A0A0A0",
            "textDim": "646E70",
            "textInput": "{{dark}}",
            "textLink": "{{accentText}}",
            "titlebarButtonBg": "{{background}}",
            "titlebarButtonBgDisabled": "{{background}}",
            "titlebarButtonBgHover": "{{background}}",
            "titlebarButtonBorder": "{{background}}",
            "titlebarButtonBorderDisabled": "{{background}}",
            "titlebarButtonBorderHover": "{{background}}",
            "titlebarButtonText": "{{buttonText}}",
            "titlebarButtonTextDisabled": "{{buttonTextDisabled}}",
            "titlebarButtonTextHover": "{{accentText}}",
            "transColor": ""
        },
        "themeAssets": {
            "logo": ""
        }
    }
}
